src/design/module_bin_to_hexa.sv
module module_bin_to_hexa (
    input  logic [3:0] binary_input,// Entrada de 4 bits dados por deep_switch
    output logic [6:0] hex_output// Salida de 7 bits para el display de 7 segmentos
);

//Asignación de la salida del display de 7 segmentos según el valor de la entrada binaria
    assign hex_output = (binary_input == 4'b0000) ? 7'b0111111 : // 0
    (binary_input == 4'b0001) ? 7'b0000110 : // 1
    (binary_input == 4'b0010) ? 7'b1011011 : // 2
    (binary_input == 4'b0011) ? 7'b1001111 : // 3
    (binary_input == 4'b0100) ? 7'b1100110 : // 4
    (binary_input == 4'b0101) ? 7'b1101101 : // 5
    (binary_input == 4'b0110) ? 7'b1111101 : // 6
    (binary_input == 4'b0111) ? 7'b0000111 : // 7
    (binary_input == 4'b1000) ? 7'b1111111 : // 8
    (binary_input == 4'b1001) ? 7'b1101111 : // 9
    (binary_input == 4'b1010) ? 7'b1110111 : // A
    (binary_input == 4'b1011) ? 7'b1111100 : // b
    (binary_input == 4'b1100) ? 7'b0111001 : // C
    (binary_input == 4'b1101) ? 7'b1011110 : // d
    (binary_input == 4'b1110) ? 7'b1111001 : // E
    (binary_input == 4'b1111) ? 7'b1110001 : // F
                              7'b0000000;    

endmodule

Proyecto_1_logico_Version_Jose/src/design/module_error_injection.sv
module module_error_injection (
    input  logic [6:0] encoded_word, // Entrada de 7 bits que representa la palabra codificada
    input  logic [2:0] error_position, // Entrada de 3 bits que indica la posición del bit a invertir
    output logic [6:0] error_injected_word // Salida de 7 bits que representa la palabra codificada con el error inyectado
);

always @(*) begin
    error_injected_word = encoded_word; // Inicialización de la salida con la palabra codificada original

    // Inversión del bit en la posición indicada por error_position
    case (error_position)
        3'b000: error_injected_word = encoded_word;      // sin error
        3'b001: error_injected_word[0] = ~encoded_word[0]; // Invertir bit 0
        3'b010: error_injected_word[1] = ~encoded_word[1]; // Misma idea hasta el 7
        3'b011: error_injected_word[2] = ~encoded_word[2];
        3'b100: error_injected_word[3] = ~encoded_word[3];
        3'b101: error_injected_word[4] = ~encoded_word[4];
        3'b110: error_injected_word[5] = ~encoded_word[5];
        3'b111: error_injected_word[6] = ~encoded_word[6]; // Invertir bit 7
    endcase
    
end
endmodule

Proyecto_1_logico_Version_Jose/src/design/module_encoder.sv
module module_encoder (
    input  logic [3:0] dip_switch, // Entrada de 4 bits dados por dip_switch
    output logic [2:0] parity_bits, // Bits de paridad calculados a partir de la entrada
    output logic [6:0] encoded_word // Salida de 7 bits que representa la palabra codificada
);
    logic x3, x5, x6, x7;
    assign{x3, x5, x6, x7} = dip_switch; // Asignación de los bits de entrada a variables individuales

    logic y1, y2, y4; //Bits de pariedad

    assign y1 = x3 ^ x5 ^ x7; // Cálculo del bit de paridad y1
    assign y2 = x3 ^ x6 ^ x7; // Cálculo del bit de paridad y2
    assign y4 = x5 ^ x6 ^ x7; // Cálculo del bit de paridad y4

assign encoded_word = {y1, y2, x3, y4, x5, x6, x7}; // Construcción de la palabra codificada con los bits de paridad y los bits de entrada
assign parity_bits = {y1, y2, y4}; // Asignación de los bits de paridad a la salida
endmodule

Proyecto_1_logico_Version_Jose/src/design/module_top.sv
module module_top (
    input  logic [3:0] codigo_gray_pi,   // DIP Switch 1: Datos (Pines 28, 27, 26, 25)
    input  logic [2:0] pos_error_pi,     // DIP Switch 2: Posición (Pines 31, 32, 33)
    input  logic button,                 // Botón S1 (Pin 3)

    // Display 1: Mensaje de Entrada
    output logic [6:0] catodo_p0,        
    output logic [0:0] anodo_p0,         // Pin 56

    // Display 2: Mensaje Transmitido (Hamming)
    output logic [6:0] catodo_trans,     
    output logic [0:0] anodo_p1,         // Pin 79

    // LEDs Integrados: Monitor de Entrada
    output logic [3:0] codigo_bin_led_p0 
);

    // Señales internas
    logic [6:0] codeword;
    logic [6:0] word_with_error;
    logic [6:0] final_word;

    // 1. Codificador Hamming (7,4)
    module_encoder encoder (
        .dip_switch(codigo_gray_pi),
        .encoded_word(codeword),
        .parity_bits() // Ignoramos esta salida aquí si no la ocupamos
    );

    // 2. Inyector de Error
    module_error_injection error_injector (
        .encoded_word(codeword),
        .error_position(pos_error_pi),
        .error_injected_word(word_with_error)
    );

    // 3. Lógica del botón (Inyectar si se presiona y la posición es 0-6)
    // NOTA: Si el error se activa sin tocar el botón, cambia "button" por "!button"
    // Cambio de línea de código porque el módulo de inyección de error ya contempla estas variables
    // También se quitó el valid_position xq no hacía falta con el cambio anterior
    assign final_word = button ? word_with_error : codeword;


    // 4. Visualización en Display 1 (Entrada Original)
    module_bin_to_hexa display_entrada (
        .binary_input(codigo_gray_pi),
        .hex_output(catodo_p0)
    );

    // 5. Visualización en Display 2 (Palabra Transmitida)
    // Mostramos los 4 bits menos significativos de la palabra Hamming
    module_bin_to_hexa display_transmision (
        .binary_input(final_word[3:0]), 
        .hex_output(catodo_trans)
    );

    // 6. Activación de Ánodos (Asumiendo Cátodo Común, enviar 1 para activar)
    assign anodo_p0 = 1'b1; 
    assign anodo_p1 = 1'b1;

    // 7. LEDs de monitoreo
    assign codigo_bin_led_p0 = codigo_gray_pi;

endmodule

Proyecto 1 logico/src/sim/module_tb_module_top.sv
`timescale 1ns/1ps

module tb_module_top;

    // Señales de estímulo
    logic [3:0] entry;
    logic inject_error;

    // Entradas al DUT (estímulos)
    module_top dut (
        .codigo_gray_pi(entry), 
        .button(inject_error),
        .catodo_p0(),            
        .anodo_p0(),
        .codigo_bin_led_p0()
    );

    // Alias para facilitar la lectura de señales INTERNAS del DUT
    // Esto permite que el TB "vea" dentro del diseño
    wire [6:0] internal_codeword = dut.codeword;
    wire [6:0] internal_word_err = dut.word_with_error;

    initial begin
        $display("====================================================================");
        $display("   MODO     | ENTRY | POS ERR |  CODEWORD | WORD W/ ERR | FINAL OUT");
        $display("====================================================================");

        // Caso 1: SIN error (Button = 0)
        inject_error = 0;
        for (int i = 0; i < 4; i++) begin // Probamos 4 casos para no saturar consola
            entry = i;
            #10;
            $display(" NORMAL     |  %b  |    -    |  %b  |      -      |  %b", 
                     entry, internal_codeword, dut.final_word);
        end

        // Caso 2: CON error inyectado (Button = 1)
        inject_error = 1;
        // Probamos una entrada con diferentes posiciones de error
        entry = 4'b1011; 
        for (int j = 0; j < 7; j++) begin
            // Nota: En tu TOP, la posición del error viene de entry[2:0]
            // Para probar distintas posiciones, debemos cambiar 'entry'
            entry = {1'b1, j[2:0]}; 
            #10;
            $display(" INYECTADO  |  %b  |    %0d    |  %b  |   %b   |  %b", 
                     entry, entry[2:0], internal_codeword, internal_word_err, dut.final_word);
        end

        // Caso 3: POSICIÓN INVÁLIDA (Pos 7 según tu lógica)
        entry = 4'b1111; // 111 -> Posición 7
        inject_error = 1;
        #10;
        $display(" INVALIDO   |  %b  |    7    |  %b  |   %b   |  %b (DEBE SER IGUAL)", 
                 entry, internal_codeword, internal_word_err, dut.final_word);

        $display("====================================================================");
        $finish;
    end

    initial begin
        $dumpfile("tb_module_top.vcd");
        $dumpvars(0, tb_module_top);
    end
endmodule

src/build/tb_module_top.vcd
$date
	Thu Apr 09 19:34:24 2026
$end
$version
	Icarus Verilog
$end
$timescale
	1ps
$end
$scope module tb_module_top $end
$var reg 4 ! entry [3:0] $end
$var reg 1 " inject_error $end
$var reg 7 # internal_codeword [6:0] $end
$var reg 7 $ internal_word_err [6:0] $end
$scope module dut $end
$var wire 1 % anodo_p0 $end
$var wire 1 & anodo_p1 $end
$var wire 1 " button $end
$var wire 4 ' codigo_bin_led_p0 [3:0] $end
$var wire 4 ( codigo_gray_pi [3:0] $end
$var wire 3 ) pos_error_pi [2:0] $end
$var wire 7 * word_with_error [6:0] $end
$var wire 7 + final_word [6:0] $end
$var wire 7 , codeword [6:0] $end
$var wire 7 - catodo_trans [6:0] $end
$var wire 7 . catodo_p0 [6:0] $end
$scope module display_entrada $end
$var wire 4 / binary_input [3:0] $end
$var wire 7 0 hex_output [6:0] $end
$upscope $end
$scope module display_transmision $end
$var wire 4 1 binary_input [3:0] $end
$var wire 7 2 hex_output [6:0] $end
$upscope $end
$scope module encoder $end
$var wire 4 3 dip_switch [3:0] $end
$var wire 1 4 y1 $end
$var wire 1 5 y2 $end
$var wire 1 6 y4 $end
$var wire 1 7 x7 $end
$var wire 1 8 x6 $end
$var wire 1 9 x5 $end
$var wire 1 : x3 $end
$var wire 3 ; parity_bits [2:0] $end
$var wire 7 < encoded_word [6:0] $end
$upscope $end
$scope module error_injector $end
$var wire 7 = encoded_word [6:0] $end
$var wire 3 > error_position [2:0] $end
$var reg 7 ? error_injected_word [6:0] $end
$upscope $end
$upscope $end
$scope begin $ivl_for_loop0 $end
$var integer 32 @ i [31:0] $end
$upscope $end
$scope begin $ivl_for_loop1 $end
$var integer 32 A j [31:0] $end
$upscope $end
$upscope $end
$enddefinitions $end
$comment Show the parameter values. $end
$dumpall
$end
#0
$dumpvars
b0 A
b0 @
b0 ?
bz >
b0 =
b0 <
b0 ;
0:
09
08
07
06
05
04
b0 3
b1000000 2
b0 1
b1000000 0
b0 /
b1000000 .
b1000000 -
b0 ,
b0 +
b0 *
bz )
b0 (
b0 '
1&
1%
bx $
bz #
0"
b0 !
$end
#10000
b10000 -
b10000 2
b1001 1
b1101001 +
b1101001 *
b1101001 ?
16
15
b111 ;
14
b1111001 .
b1111001 0
b1101001 ,
b1101001 <
b1101001 =
17
b1 '
b1 !
b1 (
b1 /
b1 3
b1 @
#20000
b1000 -
b1000 2
b1010 1
b100100 .
b100100 0
b101010 +
b101010 *
b101010 ?
16
15
b11 ;
04
18
b101010 ,
b101010 <
b101010 =
07
b10 '
b10 !
b10 (
b10 /
b10 3
b10 @
#30000
b110000 -
b110000 2
b110000 .
b110000 0
b11 1
b1000011 +
b1000011 *
b1000011 ?
06
05
b100 ;
14
b1000011 ,
b1000011 <
b1000011 =
17
b11 '
b11 !
b11 (
b11 /
b11 3
b11 @
#40000
b1000000 -
b1000000 2
b0 .
b0 0
b0 1
b1110000 +
06
b110 ;
15
b1110000 *
b1110000 ?
08
07
b1110000 ,
b1110000 <
b1110000 =
1:
b1000 '
b1000 !
b1000 (
b1000 /
b1000 3
1"
b100 @
#50000
b10000 .
b10000 0
b10000 -
b10000 2
b1001 1
b11001 +
b11001 *
b11001 ?
16
05
b1 ;
04
b11001 ,
b11001 <
b11001 =
17
b1001 '
b1001 !
b1001 (
b1001 /
b1001 3
b1 A
#60000
b1000 .
b1000 0
b1000 -
b1000 2
b1010 1
b1011010 +
b1011010 *
b1011010 ?
16
05
b101 ;
14
18
b1011010 ,
b1011010 <
b1011010 =
07
b1010 '
b1010 !
b1010 (
b1010 /
b1010 3
b10 A
#70000
b11 .
b11 0
b110000 -
b110000 2
b11 1
b110011 +
b110011 *
b110011 ?
06
15
b10 ;
04
b110011 ,
b110011 <
b110011 =
17
b1011 '
b1011 !
b1011 (
b1011 /
b1011 3
b11 A
#80000
b1000110 .
b1000110 0
b1000110 -
b1000110 2
b1100 1
b111100 +
b111100 *
b111100 ?
16
15
b11 ;
04
19
08
b111100 ,
b111100 <
b111100 =
07
b1100 '
b1100 !
b1100 (
b1100 /
b1100 3
b100 A
#90000
b100001 .
b100001 0
b10010 -
b10010 2
b101 1
b1010101 +
b1010101 *
b1010101 ?
06
05
b100 ;
14
b1010101 ,
b1010101 <
b1010101 =
17
b1101 '
b1101 !
b1101 (
b1101 /
b1101 3
b101 A
#100000
b110 .
b110 0
b10 -
b10 2
b110 1
b10110 +
b10110 *
b10110 ?
06
05
b0 ;
04
18
b10110 ,
b10110 <
b10110 =
07
b1110 '
b1110 !
b1110 (
b1110 /
b1110 3
b110 A
#110000
b1110 .
b1110 0
b1110 -
b1110 2
b1111 1
b1111111 +
b1111111 *
b1111111 ?
16
15
b111 ;
14
b1111111 ,
b1111111 <
b1111111 =
17
b1111 '
b1111 !
b1111 (
b1111 /
b1111 3
b111 A
