Proyecto 1 logico/src/design/module_bin_to_hexa.sv
module module_bin_to_hexa (
    input  logic [3:0] binary_input,// Entrada de 4 bits dados por deep_switch
    output logic [6:0] hex_output// Salida de 7 bits para el display de 7 segmentos
);

//Asignación de la salida del display de 7 segmentos según el valor de la entrada binaria
    assign hex_output = (binary_input == 4'b0000) ? 7'b1000000 : // 0
                        (binary_input == 4'b0001) ? 7'b1111001 : // 1
                        (binary_input == 4'b0010) ? 7'b0100100 : // 2
                        (binary_input == 4'b0011) ? 7'b0110000 : // 3
                        (binary_input == 4'b0100) ? 7'b0011001 : // 4
                        (binary_input == 4'b0101) ? 7'b0010010 : // 5
                        (binary_input == 4'b0110) ? 7'b0000010 : // 6
                        (binary_input == 4'b0111) ? 7'b1111000 : // 7
                        (binary_input == 4'b1000) ? 7'b0000000 : // 8
                        (binary_input == 4'b1001) ? 7'b0010000 : // 9
                        (binary_input == 4'b1010) ? 7'b0001000 : // A
                        (binary_input == 4'b1011) ? 7'b0000011 : // b
                        (binary_input == 4'b1100) ? 7'b1000110 : // C
                        (binary_input == 4'b1101) ? 7'b0100001 : // d
                        (binary_input == 4'b1110) ? 7'b0000110 : // E
                        (binary_input == 4'b1111) ? 7'b0001110 : // F
                        7'b1111111; // Caso por defecto     
endmodule

Proyecto 1 logico/src/design/module_error_injection.sv
module module_error_injection (
    input  logic [6:0] encoded_word, // Entrada de 7 bits que representa la palabra codificada
    input  logic [2:0] error_position, // Entrada de 3 bits que indica la posición del bit a invertir
    output logic [6:0] error_injected_word // Salida de 7 bits que representa la palabra codificada con el error inyectado
);

always @(*) begin
    error_injected_word = encoded_word; // Inicialización de la salida con la palabra codificada original

    // Inversión del bit en la posición indicada por error_position
    case (error_position)
        3'b000: error_injected_word = ~encoded_word[0]; // Invertir el bit 0
        3'b001: error_injected_word = ~encoded_word[1]; // Invertir el bit 1
        3'b010: error_injected_word = ~encoded_word[2]; // Invertir el bit 2
        3'b011: error_injected_word = ~encoded_word[3]; // Invertir el bit 3
        3'b100: error_injected_word = ~encoded_word[4]; // Invertir el bit 4
        3'b101: error_injected_word = ~encoded_word[5]; // Invertir el bit 5
        3'b110: error_injected_word = ~encoded_word[6]; // Invertir el bit 6
        default: error_injected_word = encoded_word; // Si no se selecciona una posición válida, no se inyecta ningún error
    endcase
    
end
endmodule

Proyecto_1_logico_Version_Jose/src/design/module_encoder.sv
module module_encoder (
    input  logic [3:0] dip_switch, // Entrada de 4 bits dados por dip_switch
    output logic [2:0] parity_bits, // Bits de paridad calculados a partir de la entrada
    output logic [6:0] encoded_word // Salida de 7 bits que representa la palabra codificada
);
    logic x3, x5, x6, x7;
    assign{x3, x5, x6, x7} = dip_switch; // Asignación de los bits de entrada a variables individuales

    logic y1, y2, y4; //Bits de pariedad

    assign y1 = x3 ^ x5 ^ x7; // Cálculo del bit de paridad y1
    assign y2 = x3 ^ x6 ^ x7; // Cálculo del bit de paridad y2
    assign y4 = x5 ^ x6 ^ x7; // Cálculo del bit de paridad y4

assign encoded_word = {y1, y2, x3, y4, x5, x6, x7}; // Construcción de la palabra codificada con los bits de paridad y los bits de entrada
assign parity_bits = {y1, y2, y4}; // Asignación de los bits de paridad a la salida
endmodule

Proyecto 1 logico/src/design/module_top.sv
module module_top (
    input  logic [3:0] codigo_gray_pi,   // DIP Switch 1: Datos (Pines 28, 27, 26, 25)
    input  logic [2:0] pos_error_pi,     // DIP Switch 2: Posición (Pines 31, 32, 33)
    input  logic button,                 // Botón S1 (Pin 3)

    // Display 1: Mensaje de Entrada
    output logic [6:0] catodo_p0,        
    output logic [0:0] anodo_p0,         // Pin 56

    // Display 2: Mensaje Transmitido (Hamming)
    output logic [6:0] catodo_trans,     
    output logic [0:0] anodo_p1,         // Pin 79

    // LEDs Integrados: Monitor de Entrada
    output logic [3:0] codigo_bin_led_p0 
);

    // Señales internas
    logic [6:0] codeword;
    logic [6:0] word_with_error;
    logic [6:0] final_word;
    logic valid_position;

    // 1. Codificador Hamming (7,4)
    module_encoder encoder (
        .dip_switch(codigo_gray_pi),
        .encoded_word(codeword),
        .parity_bits() // Ignoramos esta salida aquí si no la ocupamos
    );

    // 2. Inyector de Error
    module_error_injection error_injector (
        .encoded_word(codeword),
        .error_position(pos_error_pi),
        .error_injected_word(word_with_error)
    );

    // 3. Lógica del botón (Inyectar si se presiona y la posición es 0-6)
    // NOTA: Si el error se activa sin tocar el botón, cambia "button" por "!button"
    assign valid_position = (pos_error_pi <= 3'd6);
    assign final_word = (button && valid_position) ? word_with_error : codeword;

    // 4. Visualización en Display 1 (Entrada Original)
    module_bin_to_hexa display_entrada (
        .binary_input(codigo_gray_pi),
        .hex_output(catodo_p0)
    );

    // 5. Visualización en Display 2 (Palabra Transmitida)
    // Mostramos los 4 bits menos significativos de la palabra Hamming
    module_bin_to_hexa display_transmision (
        .binary_input(final_word[3:0]), 
        .hex_output(catodo_trans)
    );

    // 6. Activación de Ánodos (Asumiendo Cátodo Común, enviar 1 para activar)
    assign anodo_p0 = 1'b1; 
    assign anodo_p1 = 1'b1;

    // 7. LEDs de monitoreo
    assign codigo_bin_led_p0 = codigo_gray_pi;

endmodule

Proyecto 1 logico/src/sim/module_tb_module_top.sv
`timescale 1ns/1ps

module tb_module_top;

    // Señales de estímulo
    logic [3:0] entry;
    logic inject_error;

    // Entradas al DUT (estímulos)
    module_top dut (
        .codigo_gray_pi(entry), 
        .button(inject_error),
        .catodo_p0(),            
        .anodo_p0(),
        .codigo_bin_led_p0()
    );

    // Alias para facilitar la lectura de señales INTERNAS del DUT
    // Esto permite que el TB "vea" dentro del diseño
    wire [6:0] internal_codeword = dut.codeword;
    wire [6:0] internal_word_err = dut.word_with_error;

    initial begin
        $display("====================================================================");
        $display("   MODO     | ENTRY | POS ERR |  CODEWORD | WORD W/ ERR | FINAL OUT");
        $display("====================================================================");

        // Caso 1: SIN error (Button = 0)
        inject_error = 0;
        for (int i = 0; i < 4; i++) begin // Probamos 4 casos para no saturar consola
            entry = i;
            #10;
            $display(" NORMAL     |  %b  |    -    |  %b  |      -      |  %b", 
                     entry, internal_codeword, dut.final_word);
        end

        // Caso 2: CON error inyectado (Button = 1)
        inject_error = 1;
        // Probamos una entrada con diferentes posiciones de error
        entry = 4'b1011; 
        for (int j = 0; j < 7; j++) begin
            // Nota: En tu TOP, la posición del error viene de entry[2:0]
            // Para probar distintas posiciones, debemos cambiar 'entry'
            entry = {1'b1, j[2:0]}; 
            #10;
            $display(" INYECTADO  |  %b  |    %0d    |  %b  |   %b   |  %b", 
                     entry, entry[2:0], internal_codeword, internal_word_err, dut.final_word);
        end

        // Caso 3: POSICIÓN INVÁLIDA (Pos 7 según tu lógica)
        entry = 4'b1111; // 111 -> Posición 7
        inject_error = 1;
        #10;
        $display(" INVALIDO   |  %b  |    7    |  %b  |   %b   |  %b (DEBE SER IGUAL)", 
                 entry, internal_codeword, internal_word_err, dut.final_word);

        $display("====================================================================");
        $finish;
    end

    initial begin
        $dumpfile("tb_module_top.vcd");
        $dumpvars(0, tb_module_top);
    end
endmodule

Proyecto 1 logico/src/build/tb_module_top.vcd
$date
	Wed Apr 01 21:45:52 2026
$end
$version
	Icarus Verilog
$end
$timescale
	1ps
$end
$scope module tb_module_top $end
$var wire 7 ! internal_codeword [6:0] $end
$var wire 7 " internal_word_err [6:0] $end
$var reg 4 # entry [3:0] $end
$var reg 1 $ inject_error $end
$scope module dut $end
$var wire 1 % anodo_p0 $end
$var wire 1 & anodo_p1 $end
$var wire 1 $ button $end
$var wire 4 ' codigo_bin_led_p0 [3:0] $end
$var wire 4 ( codigo_gray_pi [3:0] $end
$var wire 3 ) pos_error_pi [2:0] $end
$var wire 7 * word_with_error [6:0] $end
$var wire 1 + valid_position $end
$var wire 7 , final_word [6:0] $end
$var wire 7 - codeword [6:0] $end
$var wire 7 . catodo_trans [6:0] $end
$var wire 7 / catodo_p0 [6:0] $end
$scope module display_entrada $end
$var wire 4 0 binary_input [3:0] $end
$var wire 7 1 hex_output [6:0] $end
$upscope $end
$scope module display_transmision $end
$var wire 4 2 binary_input [3:0] $end
$var wire 7 3 hex_output [6:0] $end
$upscope $end
$scope module encoder $end
$var wire 4 4 dip_switch [3:0] $end
$var wire 1 5 y1 $end
$var wire 1 6 y2 $end
$var wire 1 7 y4 $end
$var wire 1 8 x7 $end
$var wire 1 9 x6 $end
$var wire 1 : x5 $end
$var wire 1 ; x3 $end
$var wire 3 < parity_bits [2:0] $end
$var wire 7 = encoded_word [6:0] $end
$upscope $end
$scope module error_injector $end
$var wire 7 > encoded_word [6:0] $end
$var wire 3 ? error_position [2:0] $end
$var reg 7 @ error_injected_word [6:0] $end
$upscope $end
$upscope $end
$scope begin $ivl_for_loop0 $end
$var integer 32 A i [31:0] $end
$upscope $end
$scope begin $ivl_for_loop1 $end
$var integer 32 B j [31:0] $end
$upscope $end
$upscope $end
$enddefinitions $end
$comment Show the parameter values. $end
$dumpall
$end
#0
$dumpvars
b0 B
b0 A
b0 @
bz ?
b0 >
b0 =
b0 <
0;
0:
09
08
07
06
05
b0 4
b1000000 3
b0 2
b1000000 1
b0 0
b1000000 /
b1000000 .
b0 -
b0 ,
x+
b0 *
bz )
b0 (
b0 '
1&
1%
0$
b0 #
b0 "
b0 !
$end
#10000
b10000 .
b10000 3
b1001 2
b1101001 ,
b1101001 "
b1101001 *
b1101001 @
17
16
b111 <
15
b1111001 /
b1111001 1
b1101001 !
b1101001 -
b1101001 =
b1101001 >
18
b1 '
b1 #
b1 (
b1 0
b1 4
b1 A
#20000
b1000 .
b1000 3
b1010 2
b100100 /
b100100 1
b101010 ,
b101010 "
b101010 *
b101010 @
17
16
b11 <
05
19
b101010 !
b101010 -
b101010 =
b101010 >
08
b10 '
b10 #
b10 (
b10 0
b10 4
b10 A
#30000
b110000 .
b110000 3
b110000 /
b110000 1
b11 2
b1000011 ,
b1000011 "
b1000011 *
b1000011 @
07
06
b100 <
15
b1000011 !
b1000011 -
b1000011 =
b1000011 >
18
b11 '
b11 #
b11 (
b11 0
b11 4
b11 A
#40000
b0 /
b0 1
b1000000 .
b1000000 3
b0 2
07
b110 <
16
b1110000 "
b1110000 *
b1110000 @
b1110000 ,
09
08
b1110000 !
b1110000 -
b1110000 =
b1110000 >
1;
b1000 '
b1000 #
b1000 (
b1000 0
b1000 4
1$
b100 A
#50000
b10000 /
b10000 1
b10000 .
b10000 3
b1001 2
b11001 ,
b11001 "
b11001 *
b11001 @
17
06
b1 <
05
b11001 !
b11001 -
b11001 =
b11001 >
18
b1001 '
b1001 #
b1001 (
b1001 0
b1001 4
b1 B
#60000
b1000 /
b1000 1
b1000 .
b1000 3
b1010 2
b1011010 ,
b1011010 "
b1011010 *
b1011010 @
17
06
b101 <
15
19
b1011010 !
b1011010 -
b1011010 =
b1011010 >
08
b1010 '
b1010 #
b1010 (
b1010 0
b1010 4
b10 B
#70000
b11 /
b11 1
b110000 .
b110000 3
b11 2
b110011 ,
b110011 "
b110011 *
b110011 @
07
16
b10 <
05
b110011 !
b110011 -
b110011 =
b110011 >
18
b1011 '
b1011 #
b1011 (
b1011 0
b1011 4
b11 B
#80000
b1000110 /
b1000110 1
b1000110 .
b1000110 3
b1100 2
b111100 ,
b111100 "
b111100 *
b111100 @
17
16
b11 <
05
1:
09
b111100 !
b111100 -
b111100 =
b111100 >
08
b1100 '
b1100 #
b1100 (
b1100 0
b1100 4
b100 B
#90000
b100001 /
b100001 1
b10010 .
b10010 3
b101 2
b1010101 ,
b1010101 "
b1010101 *
b1010101 @
07
06
b100 <
15
b1010101 !
b1010101 -
b1010101 =
b1010101 >
18
b1101 '
b1101 #
b1101 (
b1101 0
b1101 4
b101 B
#100000
b110 /
b110 1
b10 .
b10 3
b110 2
b10110 ,
b10110 "
b10110 *
b10110 @
07
06
b0 <
05
19
b10110 !
b10110 -
b10110 =
b10110 >
08
b1110 '
b1110 #
b1110 (
b1110 0
b1110 4
b110 B
#110000
b1110 /
b1110 1
b1110 .
b1110 3
b1111 2
b1111111 ,
b1111111 "
b1111111 *
b1111111 @
17
16
b111 <
15
b1111111 !
b1111111 -
b1111111 =
b1111111 >
18
b1111 '
b1111 #
b1111 (
b1111 0
b1111 4
b111 B
