src/design/module_bin_to_hexa.sv
module module_bin_to_hexa (
    input  logic [3:0] binary_input,// Entrada de 4 bits dados por deep_switch
    output logic [6:0] hex_output// Salida de 7 bits para el display de 7 segmentos
);

//Asignación de la salida del display de 7 segmentos según el valor de la entrada binaria
    assign hex_output = (binary_input == 4'b0000) ? 7'b0111111 : // 0
    (binary_input == 4'b0001) ? 7'b0000110 : // 1
    (binary_input == 4'b0010) ? 7'b1011011 : // 2
    (binary_input == 4'b0011) ? 7'b1001111 : // 3
    (binary_input == 4'b0100) ? 7'b1100110 : // 4
    (binary_input == 4'b0101) ? 7'b1101101 : // 5
    (binary_input == 4'b0110) ? 7'b1111101 : // 6
    (binary_input == 4'b0111) ? 7'b0000111 : // 7
    (binary_input == 4'b1000) ? 7'b1111111 : // 8
    (binary_input == 4'b1001) ? 7'b1101111 : // 9
    (binary_input == 4'b1010) ? 7'b1110111 : // A
    (binary_input == 4'b1011) ? 7'b1111100 : // b
    (binary_input == 4'b1100) ? 7'b0111001 : // C
    (binary_input == 4'b1101) ? 7'b1011110 : // d
    (binary_input == 4'b1110) ? 7'b1111001 : // E
    (binary_input == 4'b1111) ? 7'b1110001 : // F
                              7'b0000000;    

endmodule

Proyecto_1_logico_Version_Jose/src/sim/tb_bin_to_hexa.sv
`timescale 1ns/1ps

module tb_bin_to_hexa;

    logic [3:0] binary_input;
    logic [6:0] hex_output;

    module_bin_to_hexa dut (
        .binary_input(binary_input),
        .hex_output(hex_output)
    );

    initial begin
        $dumpfile("tb_bin_to_hexa.vcd");
        $dumpvars(0, tb_bin_to_hexa);

        $display("==============================================");
        $display("Inicio testbench module_bin_to_hexa");
        $display("==============================================");

        binary_input = 4'b0000; #10;
        $display("in=%b out=%b", binary_input, hex_output);

        binary_input = 4'b0001; #10;
        $display("in=%b out=%b", binary_input, hex_output);

        binary_input = 4'b0010; #10;
        $display("in=%b out=%b", binary_input, hex_output);

        binary_input = 4'b0011; #10;
        $display("in=%b out=%b", binary_input, hex_output);

        binary_input = 4'b0100; #10;
        $display("in=%b out=%b", binary_input, hex_output);

        binary_input = 4'b0101; #10;
        $display("in=%b out=%b", binary_input, hex_output);

        binary_input = 4'b0110; #10;
        $display("in=%b out=%b", binary_input, hex_output);

        binary_input = 4'b0111; #10;
        $display("in=%b out=%b", binary_input, hex_output);

        binary_input = 4'b1000; #10;
        $display("in=%b out=%b", binary_input, hex_output);

        binary_input = 4'b1001; #10;
        $display("in=%b out=%b", binary_input, hex_output);

        binary_input = 4'b1010; #10;
        $display("in=%b out=%b", binary_input, hex_output);

        binary_input = 4'b1011; #10;
        $display("in=%b out=%b", binary_input, hex_output);

        binary_input = 4'b1100; #10;
        $display("in=%b out=%b", binary_input, hex_output);

        binary_input = 4'b1101; #10;
        $display("in=%b out=%b", binary_input, hex_output);

        binary_input = 4'b1110; #10;
        $display("in=%b out=%b", binary_input, hex_output);

        binary_input = 4'b1111; #10;
        $display("in=%b out=%b", binary_input, hex_output);

        $display("==============================================");
        $display("Fin testbench module_bin_to_hexa");
        $display("==============================================");

        $finish;
    end

endmodule

Proyecto_1_logico_Version_Jose/tb_bin_to_hexa.vcd
$date
	Sun Apr 05 18:46:15 2026
$end
$version
	Icarus Verilog
$end
$timescale
	1ps
$end
$scope module tb_bin_to_hexa $end
$var wire 7 ! hex_output [6:0] $end
$var reg 4 " binary_input [3:0] $end
$scope module dut $end
$var wire 4 # binary_input [3:0] $end
$var wire 7 $ hex_output [6:0] $end
$upscope $end
$upscope $end
$enddefinitions $end
$comment Show the parameter values. $end
$dumpall
$end
#0
$dumpvars
b1000000 $
b0 #
b0 "
b1000000 !
$end
#10000
b1111001 !
b1111001 $
b1 "
b1 #
#20000
b100100 !
b100100 $
b10 "
b10 #
#30000
b110000 !
b110000 $
b11 "
b11 #
#40000
b11001 !
b11001 $
b100 "
b100 #
#50000
b10010 !
b10010 $
b101 "
b101 #
#60000
b10 !
b10 $
b110 "
b110 #
#70000
b1111000 !
b1111000 $
b111 "
b111 #
#80000
b0 !
b0 $
b1000 "
b1000 #
#90000
b10000 !
b10000 $
b1001 "
b1001 #
#100000
b1000 !
b1000 $
b1010 "
b1010 #
#110000
b11 !
b11 $
b1011 "
b1011 #
#120000
b1000110 !
b1000110 $
b1100 "
b1100 #
#130000
b100001 !
b100001 $
b1101 "
b1101 #
#140000
b110 !
b110 $
b1110 "
b1110 #
#150000
b1110 !
b1110 $
b1111 "
b1111 #
