Proyecto_1_logico_Version_Jose/src/design/module_error_injection.sv
module module_error_injection (
    input  logic [6:0] encoded_word, // Entrada de 7 bits que representa la palabra codificada
    input  logic [2:0] error_position, // Entrada de 3 bits que indica la posición del bit a invertir
    output logic [6:0] error_injected_word // Salida de 7 bits que representa la palabra codificada con el error inyectado
);

always @(*) begin
    error_injected_word = encoded_word; // Inicialización de la salida con la palabra codificada original

    // Inversión del bit en la posición indicada por error_position
    case (error_position)
        3'b000: error_injected_word = encoded_word;      // sin error
        3'b001: error_injected_word[0] = ~encoded_word[0]; // Invertir bit 0
        3'b010: error_injected_word[1] = ~encoded_word[1]; // Misma idea hasta el 7
        3'b011: error_injected_word[2] = ~encoded_word[2];
        3'b100: error_injected_word[3] = ~encoded_word[3];
        3'b101: error_injected_word[4] = ~encoded_word[4];
        3'b110: error_injected_word[5] = ~encoded_word[5];
        3'b111: error_injected_word[6] = ~encoded_word[6]; // Invertir bit 7
    endcase
    
end
endmodule

Proyecto_1_logico_Version_Jose/src/sim/tb_error_injection.sv
`timescale 1ns/1ps

module tb_error_injection;

    logic [6:0] encoded_word;
    logic [2:0] error_position;
    logic [6:0] error_injected_word;

    module_error_injection dut (
        .encoded_word(encoded_word),
        .error_position(error_position),
        .error_injected_word(error_injected_word)
    );

    initial begin
        $dumpfile("tb_error_injection.vcd");
        $dumpvars(0, tb_error_injection);

        $display("==============================================");
        $display("Inicio testbench module_error_injection");
        $display("==============================================");

        // Palabra base
        encoded_word = 7'b0110011;

        // Caso 1: sin error
        error_position = 3'b000; #10;
        $display("pos=%b in=%b out=%b", error_position, encoded_word, error_injected_word);

        // Caso 2: invertir bit 0
        error_position = 3'b001; #10;
        $display("pos=%b in=%b out=%b", error_position, encoded_word, error_injected_word);

        // Caso 3: invertir bit 1
        error_position = 3'b010; #10;
        $display("pos=%b in=%b out=%b", error_position, encoded_word, error_injected_word);

        // Caso 4: invertir bit 2
        error_position = 3'b011; #10;
        $display("pos=%b in=%b out=%b", error_position, encoded_word, error_injected_word);

        // Caso 5: invertir bit 3
        error_position = 3'b100; #10;
        $display("pos=%b in=%b out=%b", error_position, encoded_word, error_injected_word);

        // Caso 6: invertir bit 4
        error_position = 3'b101; #10;
        $display("pos=%b in=%b out=%b", error_position, encoded_word, error_injected_word);

        // Caso 7: invertir bit 5
        error_position = 3'b110; #10;
        $display("pos=%b in=%b out=%b", error_position, encoded_word, error_injected_word);

        // Caso 8: invertir bit 6
        error_position = 3'b111; #10;
        $display("pos=%b in=%b out=%b", error_position, encoded_word, error_injected_word);

        $display("==============================================");
        $display("Fin testbench module_error_injection");
        $display("==============================================");

        $finish;
    end

endmodule

Proyecto_1_logico_Version_Jose/tb_error_injection.vcd
$date
	Sun Apr 05 18:15:21 2026
$end
$version
	Icarus Verilog
$end
$timescale
	1ps
$end
$scope module tb_error_injection $end
$var wire 7 ! error_injected_word [6:0] $end
$var reg 7 " encoded_word [6:0] $end
$var reg 3 # error_position [2:0] $end
$scope module dut $end
$var wire 7 $ encoded_word [6:0] $end
$var wire 3 % error_position [2:0] $end
$var reg 7 & error_injected_word [6:0] $end
$upscope $end
$upscope $end
$enddefinitions $end
$comment Show the parameter values. $end
$dumpall
$end
#0
$dumpvars
b110011 &
b0 %
b110011 $
b0 #
b110011 "
b110011 !
$end
#10000
b110010 !
b110010 &
b1 #
b1 %
#20000
b110001 !
b110001 &
b10 #
b10 %
#30000
b110111 !
b110111 &
b11 #
b11 %
#40000
b111011 !
b111011 &
b100 #
b100 %
#50000
b100011 !
b100011 &
b101 #
b101 %
#60000
b10011 !
b10011 &
b110 #
b110 %
#70000
b1110011 !
b1110011 &
b111 #
b111 %
